fingerprints/__init__.py
fingerprints/cleanup.py
fingerprints/constants.py
fingerprints/fingerprint.py
fingerprints/py.typed
fingerprints/types/__init__.py
fingerprints/types/check.py
fingerprints/types/common.py
fingerprints/types/compile.py
fingerprints/types/data.py
fingerprints/types/replacer.py
fingerprints/types/types.yml
fingerprints-1.3.0.dist-info/METADATA
fingerprints-1.3.0.dist-info/WHEEL
fingerprints-1.3.0.dist-info/licenses/LICENSE
fingerprints-1.3.0.dist-info/RECORD
