Metadata-Version: 2.4
Name: fingerprints
Version: 1.3.0
Summary: A library to generate entity fingerprints.
Project-URL: Documentation, https://github.com/opensanctions/fingerprints/
Project-URL: Repository, https://github.com/opensanctions/fingerprints.git
Project-URL: Issues, https://github.com/opensanctions/fingerprints/issues
Author-email: OpenSanctions <info@opensanctions.org>
License: The MIT License (MIT)
License-File: LICENSE
Classifier: Intended Audience :: Developers
Classifier: License :: OSI Approved :: MIT License
Classifier: Operating System :: OS Independent
Classifier: Programming Language :: Python :: 3.11
Classifier: Programming Language :: Python :: 3.12
Requires-Python: >=3.10
Requires-Dist: normality<4.0.0,>=3.0.1
Provides-Extra: dev
Requires-Dist: build; extra == 'dev'
Requires-Dist: bump2version; extra == 'dev'
Requires-Dist: coverage>=4.1; extra == 'dev'
Requires-Dist: mypy; extra == 'dev'
Requires-Dist: pytest; extra == 'dev'
Requires-Dist: pytest-cov; extra == 'dev'
Requires-Dist: pyyaml<7.0.0,>=5.0.0; extra == 'dev'
Requires-Dist: ruff; extra == 'dev'
Requires-Dist: types-pyyaml; extra == 'dev'
